src/__init__.py
src/cli.py
src/core.py
src/logging_utils.py
src/actions/__init__.py
src/actions/add.py
src/actions/execute_script.py
src/actions/init.py
src/actions/install.py
src/actions/remove.py
src/actions/show.py
python_barn-0.11.0.dist-info/METADATA
python_barn-0.11.0.dist-info/WHEEL
python_barn-0.11.0.dist-info/entry_points.txt
python_barn-0.11.0.dist-info/top_level.txt
python_barn-0.11.0.dist-info/RECORD
