Metadata-Version: 2.1
Name: python-barn
Version: 0.11.0
Summary: A wrapper for pip, to give better utils to python projects dependency management
Home-page: https://github.com/JacopoMadaluni/barn
Author: Jacopo Madaluni
Author-email: jacopo.madaluni@gmail.com
Classifier: Development Status :: 3 - Alpha
Classifier: Intended Audience :: Developers
Classifier: License :: OSI Approved :: MIT License
Classifier: Programming Language :: Python :: 3.9
Requires-Python: >=3.9
Requires-Dist: PyYAML ==6.0
